mbed_greentea/__init__.py
mbed_greentea/__main__.py
mbed_greentea/cmake_handlers.py
mbed_greentea/mbed_common_api.py
mbed_greentea/mbed_coverage_api.py
mbed_greentea/mbed_greentea_cli.py
mbed_greentea/mbed_greentea_dlm.py
mbed_greentea/mbed_greentea_hooks.py
mbed_greentea/mbed_greentea_log.py
mbed_greentea/mbed_report_api.py
mbed_greentea/mbed_target_info.py
mbed_greentea/mbed_test_api.py
mbed_greentea/mbed_yotta_api.py
mbed_greentea/mbed_yotta_module_parse.py
mbed_greentea/tests_spec.py
test/__init__.py
test/basic.py
test/mbed_gt_cli.py
test/mbed_gt_cmake_handlers.py
test/mbed_gt_coverage_api.py
test/mbed_gt_greentea_dlm.py
test/mbed_gt_hooks.py
test/mbed_gt_report_api.py
test/mbed_gt_target_info.py
test/mbed_gt_test_api.py
test/mbed_gt_test_filtered_test_list.py
test/mbed_gt_tests_spec.py
test/mbed_gt_yotta_api.py
test/mbed_gt_yotta_config.py
test/mbed_gt_yotta_module.py
test/report_api.py
mbed_greentea-1.8.14.dist-info/METADATA
mbed_greentea-1.8.14.dist-info/WHEEL
mbed_greentea-1.8.14.dist-info/entry_points.txt
mbed_greentea-1.8.14.dist-info/top_level.txt
mbed_greentea-1.8.14.dist-info/RECORD
