Metadata-Version: 2.1
Name: mbed-greentea
Version: 1.8.14
Summary: mbed 3.0 onwards test suite, codename Greentea. The test suite is a collection of tools that enable automated testing on mbed-enabled platforms
Home-page: https://github.com/ARMmbed/mbed-os-tools
Author: Anna Bridge, Qinghao Shi
Author-email: Anna.Bridge@arm.com, qinghao.shi@arm.com
Maintainer: Anna Bridge, Qinghao Shi
Maintainer-email: Anna.Bridge@arm.com, qinghao.shi@arm.com
License: Apache-2.0
Platform: UNKNOWN
Classifier: Development Status :: 5 - Production/Stable
Classifier: Intended Audience :: Developers
Classifier: License :: OSI Approved :: Apache Software License
Classifier: Programming Language :: Python :: 2
Classifier: Programming Language :: Python :: 2.7
Classifier: Programming Language :: Python :: 3
Classifier: Programming Language :: Python :: 3.5
Classifier: Programming Language :: Python :: 3.6
Classifier: Programming Language :: Python :: 3.7
Classifier: Programming Language :: Python
Classifier: Topic :: Software Development :: Build Tools
Classifier: Topic :: Software Development :: Embedded Systems
Classifier: Topic :: Software Development :: Testing
Requires-Python: >=2.7.10, !=3.0.*, !=3.1.*, !=3.2.*, !=3.3.*, !=3.4.*, <4
Requires-Dist: mbed-os-tools (>=0.0.9)
Requires-Dist: mbed-host-tests (<2,>=1.5.0)
